{
  "Id": 10000129,
  "PromoteId": 129,
  "Sort": 117,
  "Body": 1,
  "Icon": "UI_AvatarIcon_Lohen",
  "SideIcon": "UI_AvatarIcon_Side_Lohen",
  "Name": "Лоэн",
  "Description": "Заместитель капитана отряда дальнего боя Ордо Фавониус, рыцарь, действующий нестандартно и предпочитающий необычные тактики.",
  "BeginTime": "2026-06-09T18:00:00+08:00",
  "Quality": 5,
  "Weapon": 13,
  "BaseValue": {
    "HpBase": 1000.986,
    "AttackBase": 26.8128,
    "DefenseBase": 61.0266
  },
  "GrowCurves": [
    {
      "Type": 1,
      "Value": 21
    },
    {
      "Type": 4,
      "Value": 31
    },
    {
      "Type": 7,
      "Value": 21
    }
  ],
  "SkillDepot": {
    "Arkhe": 0,
    "Skills": [
      {
        "GroupId": 12931,
        "Proud": {
          "Descriptions": [
            "Урон атаки 1|{param1:F1P}",
            "Урон атаки 2|{param2:F1P}",
            "Урон атаки 3|{param3:F1P}×3",
            "Урон атаки 4|{param4:F1P}",
            "Урон атаки 5|{param5:F1P}+{param6:F1P}",
            "Урон заряженной атаки|{param7:F1P}×2",
            "Потребление выносливости|{param8:F1} ед.",
            "Урон в падении|{param9:F1P}",
            "Урон низкого/высокого удара|{param10:P}/{param11:P}"
          ],
          "Parameters": [
            {
              "Id": 1293101,
              "Level": 1,
              "Parameters": [
                0.539917,
                0.564427,
                0.254199,
                0.752259,
                0.368579,
                0.552868,
                0.65876,
                25,
                0.639324,
                1.278377,
                1.596762
              ]
            },
            {
              "Id": 1293102,
              "Level": 2,
              "Parameters": [
                0.583863,
                0.610368,
                0.274889,
                0.81349,
                0.398579,
                0.597869,
                0.71238,
                25,
                0.691362,
                1.382431,
                1.726731
              ]
            },
            {
              "Id": 1293103,
              "Level": 3,
              "Parameters": [
                0.62781,
                0.65631,
                0.29558,
                0.87472,
                0.42858,
                0.64287,
                0.766,
                25,
                0.7434,
                1.486485,
                1.8567
              ]
            },
            {
              "Id": 1293104,
              "Level": 4,
              "Parameters": [
                0.690591,
                0.721941,
                0.325138,
                0.962192,
                0.471438,
                0.707157,
                0.8426,
                25,
                0.81774,
                1.635134,
                2.04237
              ]
            },
            {
              "Id": 1293105,
              "Level": 5,
              "Parameters": [
                0.734538,
                0.767883,
                0.345829,
                1.023422,
                0.501439,
                0.752158,
                0.89622,
                25,
                0.869778,
                1.739187,
                2.172339
              ]
            },
            {
              "Id": 1293106,
              "Level": 6,
              "Parameters": [
                0.784763,
                0.820387,
                0.369475,
                1.0934,
                0.535725,
                0.803588,
                0.9575,
                25,
                0.92925,
                1.858106,
                2.320875
              ]
            },
            {
              "Id": 1293107,
              "Level": 7,
              "Parameters": [
                0.853822,
                0.892582,
                0.401989,
                1.189619,
                0.582869,
                0.874303,
                1.04176,
                25,
                1.011024,
                2.02162,
                2.525112
              ]
            },
            {
              "Id": 1293108,
              "Level": 8,
              "Parameters": [
                0.922881,
                0.964776,
                0.434503,
                1.285838,
                0.630013,
                0.945019,
                1.12602,
                25,
                1.092798,
                2.185133,
                2.729349
              ]
            },
            {
              "Id": 1293109,
              "Level": 9,
              "Parameters": [
                0.99194,
                1.03697,
                0.467016,
                1.382058,
                0.677156,
                1.015735,
                1.21028,
                25,
                1.174572,
                2.348646,
                2.933586
              ]
            },
            {
              "Id": 1293110,
              "Level": 10,
              "Parameters": [
                1.067277,
                1.115727,
                0.502486,
                1.487024,
                0.728586,
                1.092879,
                1.3022,
                25,
                1.26378,
                2.527025,
                3.15639
              ]
            },
            {
              "Id": 1293111,
              "Level": 11,
              "Parameters": [
                1.142614,
                1.194484,
                0.537956,
                1.59199,
                0.780016,
                1.170023,
                1.39412,
                25,
                1.352988,
                2.705403,
                3.379194
              ]
            },
            {
              "Id": 1293112,
              "Level": 12,
              "Parameters": [
                1.217951,
                1.273241,
                0.573425,
                1.696957,
                0.831445,
                1.247168,
                1.48604,
                25,
                1.442196,
                2.883781,
                3.601998
              ]
            },
            {
              "Id": 1293113,
              "Level": 13,
              "Parameters": [
                1.293289,
                1.351999,
                0.608895,
                1.801923,
                0.882875,
                1.324312,
                1.57796,
                25,
                1.531404,
                3.062159,
                3.824802
              ]
            },
            {
              "Id": 1293114,
              "Level": 14,
              "Parameters": [
                1.368626,
                1.430756,
                0.644364,
                1.90689,
                0.934304,
                1.401457,
                1.66988,
                25,
                1.620612,
                3.240537,
                4.047606
              ]
            },
            {
              "Id": 1293115,
              "Level": 15,
              "Parameters": [
                1.443963,
                1.509513,
                0.679834,
                2.011856,
                0.985734,
                1.478601,
                1.7618,
                25,
                1.70982,
                3.418915,
                4.27041
              ]
            }
          ],
          "Display": 0
        },
        "Id": 11291,
        "Name": "Копьё Фавония: Преданная клятва",
        "Description": "<color=#FFD780FF>Обычная атака:</color>\nДо пяти последовательных ударов.\n\n<color=#FFD780FF>Заряженная атака:</color>\nТратит определённое количество выносливости и выполняет удар вперёд.\n\n<color=#FFD780FF>Атака в падении:</color>\nСтремительно падает на землю, атакуя всех врагов на пути. Приземлившись, наносит урон по площади.",
        "Icon": "Skill_A_03"
      },
      {
        "GroupId": 12932,
        "Proud": {
          "Descriptions": [
            "Урон атаки 1|{param1:F1P}",
            "Урон атаки 2|{param2:F1P}",
            "Урон атаки 3|{param3:F1P}×3",
            "Урон атаки 4|{param4:F1P}",
            "Урон атаки 5|{param5:F1P}+{param6:F1P}",
            "Урон заряженной атаки|{param7:F1P}×2",
            "Потребление выносливости|{param8:F1} ед.",
            "Урон в падении|{param9:F1P}",
            "Урон низкого/высокого удара|{param10:P}/{param11:P}",
            "Длительность Мастерского хода|{param12:F1} сек.",
            "Урон навыка Врезано в кость и сердце|{param17:F1P}×4",
            "Увеличение исходного урона за ед. Жажды победы|{param18:F2P}",
            "Время отката|{param19:F1} сек."
          ],
          "Parameters": [
            {
              "Id": 1293201,
              "Level": 1,
              "Parameters": [
                0.809875,
                0.84664,
                0.381298,
                1.128389,
                0.552868,
                0.829302,
                0.98814,
                10,
                0.639324,
                1.278377,
                1.596762,
                13,
                17,
                17,
                10,
                20,
                0.6,
                0.004,
                18
              ]
            },
            {
              "Id": 1293202,
              "Level": 2,
              "Parameters": [
                0.875795,
                0.915552,
                0.412334,
                1.220234,
                0.597869,
                0.896804,
                1.06857,
                10,
                0.691362,
                1.382431,
                1.726731,
                13,
                17,
                17,
                10,
                20,
                0.645,
                0.004,
                18
              ]
            },
            {
              "Id": 1293203,
              "Level": 3,
              "Parameters": [
                0.941715,
                0.984465,
                0.44337,
                1.31208,
                0.64287,
                0.964305,
                1.149,
                10,
                0.7434,
                1.486485,
                1.8567,
                13,
                17,
                17,
                10,
                20,
                0.69,
                0.004,
                18
              ]
            },
            {
              "Id": 1293204,
              "Level": 4,
              "Parameters": [
                1.035887,
                1.082912,
                0.487707,
                1.443288,
                0.707157,
                1.060736,
                1.2639,
                10,
                0.81774,
                1.635134,
                2.04237,
                13,
                17,
                17,
                10,
                20,
                0.75,
                0.004,
                18
              ]
            },
            {
              "Id": 1293205,
              "Level": 5,
              "Parameters": [
                1.101807,
                1.151824,
                0.518743,
                1.535134,
                0.752158,
                1.128237,
                1.34433,
                10,
                0.869778,
                1.739187,
                2.172339,
                13,
                17,
                17,
                10,
                20,
                0.795,
                0.004,
                18
              ]
            },
            {
              "Id": 1293206,
              "Level": 6,
              "Parameters": [
                1.177144,
                1.230581,
                0.554212,
                1.6401,
                0.803588,
                1.205381,
                1.43625,
                10,
                0.92925,
                1.858106,
                2.320875,
                13,
                17,
                17,
                10,
                20,
                0.84,
                0.004,
                18
              ]
            },
            {
              "Id": 1293207,
              "Level": 7,
              "Parameters": [
                1.280732,
                1.338872,
                0.602983,
                1.784429,
                0.874303,
                1.311455,
                1.56264,
                10,
                1.011024,
                2.02162,
                2.525112,
                13,
                17,
                17,
                10,
                20,
                0.9,
                0.004,
                18
              ]
            },
            {
              "Id": 1293208,
              "Level": 8,
              "Parameters": [
                1.384321,
                1.447164,
                0.651754,
                1.928758,
                0.945019,
                1.417528,
                1.68903,
                10,
                1.092798,
                2.185133,
                2.729349,
                13,
                17,
                17,
                10,
                20,
                0.96,
                0.004,
                18
              ]
            },
            {
              "Id": 1293209,
              "Level": 9,
              "Parameters": [
                1.48791,
                1.555455,
                0.700525,
                2.073086,
                1.015735,
                1.523602,
                1.81542,
                10,
                1.174572,
                2.348646,
                2.933586,
                13,
                17,
                17,
                10,
                20,
                1.02,
                0.004,
                18
              ]
            },
            {
              "Id": 1293210,
              "Level": 10,
              "Parameters": [
                1.600915,
                1.67359,
                0.753729,
                2.230536,
                1.092879,
                1.639319,
                1.9533,
                10,
                1.26378,
                2.527025,
                3.15639,
                13,
                17,
                17,
                10,
                20,
                1.08,
                0.004,
                18
              ]
            },
            {
              "Id": 1293211,
              "Level": 11,
              "Parameters": [
                1.713921,
                1.791726,
                0.806933,
                2.387986,
                1.170023,
                1.755035,
                2.09118,
                10,
                1.352988,
                2.705403,
                3.379194,
                13,
                17,
                17,
                10,
                20,
                1.14,
                0.004,
                18
              ]
            },
            {
              "Id": 1293212,
              "Level": 12,
              "Parameters": [
                1.826927,
                1.909862,
                0.860138,
                2.545435,
                1.247168,
                1.870752,
                2.22906,
                10,
                1.442196,
                2.883781,
                3.601998,
                13,
                17,
                17,
                10,
                20,
                1.2,
                0.004,
                18
              ]
            },
            {
              "Id": 1293213,
              "Level": 13,
              "Parameters": [
                1.939933,
                2.027998,
                0.913342,
                2.702885,
                1.324312,
                1.986468,
                2.36694,
                10,
                1.531404,
                3.062159,
                3.824802,
                13,
                17,
                17,
                10,
                20,
                1.275,
                0.004,
                18
              ]
            },
            {
              "Id": 1293214,
              "Level": 14,
              "Parameters": [
                2.052939,
                2.146134,
                0.966547,
                2.860334,
                1.401457,
                2.102185,
                2.50482,
                10,
                1.620612,
                3.240537,
                4.047606,
                13,
                17,
                17,
                10,
                20,
                1.35,
                0.004,
                18
              ]
            },
            {
              "Id": 1293215,
              "Level": 15,
              "Parameters": [
                2.165944,
                2.264269,
                1.019751,
                3.017784,
                1.478601,
                2.217901,
                2.6427,
                10,
                1.70982,
                3.418915,
                4.27041,
                13,
                17,
                17,
                10,
                20,
                1.425,
                0.004,
                18
              ]
            }
          ],
          "Display": 0
        },
        "Id": 11292,
        "Name": "Непредвиденный удар",
        "Description": "Лоэн ищет уязвимости и переходит в режим {LINK#N11290001}<color=#FFD780FF>Мастерского хода</color>{/LINK}. В этом режиме:\n· Лоэн накапливает {LINK#N11290003}<color=#FFD780FF>Ликование</color>{/LINK}, которое позволяет ему активировать особый элементальный навык {LINK#N11290002}<color=#FFD780FF>Врезано в кость и сердце</color>{/LINK}.\n· Другие персонажи отряда поблизости накапливают Лоэну {LINK#N11290004}<color=#FFD780FF>Жажду победы</color>{/LINK}, повышая урон навыка <color=#FFD780FF>Врезано в кость и сердце</color>.\nПосле максимум 3 применений навыка <color=#FFD780FF>Врезано в кость и сердце</color> в режиме <color=#FFD780FF>Мастерского хода</color> Лоэн перестаёт получать <color=#FFD780FF>Ликование</color>.\n\n<i>«Рыцарство? Ха, это действительно отличная приманка. Когда враг мечтает о честном поединке, он и представить не может, какой его ожидает \"сюрприз\"».</i>",
        "Icon": "Skill_S_Lohen_01"
      }
    ],
    "SpecialSkills": [
      {
        "GroupId": 12951,
        "Proud": {
          "Descriptions": [],
          "Parameters": [
            {
              "Id": 1295101,
              "Level": 1,
              "Parameters": [
                0.5,
                0.4,
                6
              ]
            }
          ],
          "Display": 3
        },
        "Id": 1295101,
        "Name": "Ведьмин ритуал кануна: Незаживающий шип",
        "Description": "Выполнив <color=#FFD780FF>Уроки ведьм: О различных врагах</color>, Лоэн станет <color=#FFD780FF>Ведьмовским</color> персонажем. Если в отряде хотя бы 2 Ведьмовских персонажа, активируется эффект <color=#FFD780FF>Ведьмовство: Тайный обряд</color>, который усиливает Ведьмовских персонажей.\n\n<color=#FFD780FF>Ведьмовство: Тайный обряд</color>\nКогда Лоэн попадает по противнику особым элементальным навыком {LINK#N11290002}<color=#FFD780FF>Врезано в кость и сердце</color>{/LINK} или применяет взрыв стихии <color=#FFD780FF>Вынесение приговора</color>, а его {LINK#N11290004}<color=#FFD780FF>Жажда победы</color>{/LINK} не менее 50% от максимума, то урон обычной и заряженной атак Лоэна повышается на 40% на 6 сек.",
        "Icon": "UI_Talent_S_Lohen_07"
      }
    ],
    "EnergySkill": {
      "GroupId": 12939,
      "Proud": {
        "Descriptions": [
          "Урон навыка|{param1:F1P}×6",
          "Увеличение исходного урона за ед. Жажды победы|{param2:F2P}",
          "Время отката|{param3:F1} сек.",
          "Потребление энергии|{param4:I}"
        ],
        "Parameters": [
          {
            "Id": 1293901,
            "Level": 1,
            "Parameters": [
              1.188,
              0.004,
              15,
              60
            ]
          },
          {
            "Id": 1293902,
            "Level": 2,
            "Parameters": [
              1.2771,
              0.004,
              15,
              60
            ]
          },
          {
            "Id": 1293903,
            "Level": 3,
            "Parameters": [
              1.3662,
              0.004,
              15,
              60
            ]
          },
          {
            "Id": 1293904,
            "Level": 4,
            "Parameters": [
              1.485,
              0.004,
              15,
              60
            ]
          },
          {
            "Id": 1293905,
            "Level": 5,
            "Parameters": [
              1.5741,
              0.004,
              15,
              60
            ]
          },
          {
            "Id": 1293906,
            "Level": 6,
            "Parameters": [
              1.6632,
              0.004,
              15,
              60
            ]
          },
          {
            "Id": 1293907,
            "Level": 7,
            "Parameters": [
              1.782,
              0.004,
              15,
              60
            ]
          },
          {
            "Id": 1293908,
            "Level": 8,
            "Parameters": [
              1.9008,
              0.004,
              15,
              60
            ]
          },
          {
            "Id": 1293909,
            "Level": 9,
            "Parameters": [
              2.0196,
              0.004,
              15,
              60
            ]
          },
          {
            "Id": 1293910,
            "Level": 10,
            "Parameters": [
              2.1384,
              0.004,
              15,
              60
            ]
          },
          {
            "Id": 1293911,
            "Level": 11,
            "Parameters": [
              2.2572,
              0.004,
              15,
              60
            ]
          },
          {
            "Id": 1293912,
            "Level": 12,
            "Parameters": [
              2.376,
              0.004,
              15,
              60
            ]
          },
          {
            "Id": 1293913,
            "Level": 13,
            "Parameters": [
              2.5245,
              0.004,
              15,
              60
            ]
          },
          {
            "Id": 1293914,
            "Level": 14,
            "Parameters": [
              2.673,
              0.004,
              15,
              60
            ]
          },
          {
            "Id": 1293915,
            "Level": 15,
            "Parameters": [
              2.8215,
              0.004,
              15,
              60
            ]
          }
        ],
        "Display": 0
      },
      "Id": 11295,
      "Name": "Вынесение приговора",
      "Description": "Выполняет стремительную серию ударов вперёд, расходуя всю {LINK#N11290004}<color=#FFD780FF>Жажду победы</color>{/LINK} и нанося <color=#99FFFFFF>Крио урон</color>. Этот урон повышается в зависимости от количества израсходованной <color=#FFD780FF>Жажды победы</color>. Если во время применения навыка Лоэн находится в режиме {LINK#N11290001}<color=#FFD780FF>Мастерского хода</color>{/LINK}, то текущий <color=#FFD780FF>Мастерский ход</color> продлевается на 1,65 сек.\n\n<i>«У тебя всё? Жаль, я только вошёл во вкус...»</i>",
      "Icon": "Skill_E_Lohen_01"
    },
    "Inherents": [
      {
        "GroupId": 12921,
        "Proud": {
          "Descriptions": [],
          "Parameters": [
            {
              "Id": 1292101,
              "Level": 1,
              "Parameters": [
                30,
                60
              ]
            }
          ],
          "Display": 1
        },
        "Id": 1292101,
        "Name": "Запрет на допросы",
        "Description": "Если другие персонажи отряда поблизости накапливают Лоэну {LINK#N11290004}<color=#FFD780FF>Жажду победы</color>{/LINK}, нанося урон, когда Лоэн находится в режиме {LINK#N11290001}<color=#FFD780FF>Мастерского хода</color>{/LINK}, а данный урон не менее 3000% от базовой атаки Лоэна, то он дополнительно получает 60 ед. <color=#FFD780FF>Жажды победы</color>.",
        "Icon": "UI_Talent_S_Lohen_05"
      },
      {
        "GroupId": 12922,
        "Proud": {
          "Descriptions": [],
          "Parameters": [
            {
              "Id": 1292201,
              "Level": 1,
              "Parameters": [
                0.15,
                0.15,
                8
              ]
            }
          ],
          "Display": 1
        },
        "Id": 1292201,
        "Name": "Шуточный шедевр",
        "Description": "Когда Лоэн пребывает в режиме {LINK#N11290001}<color=#FFD780FF>Мастерского хода</color>{/LINK}, после того как другой персонаж отряда поблизости активирует на противнике <color=#99FFFFFF>реакцию Крио</color>, сила атаки этого персонажа и Лоэна на 8 сек. повышается на 15%.",
        "Icon": "UI_Talent_S_Lohen_06"
      },
      {
        "GroupId": 12923,
        "Proud": {
          "Descriptions": [],
          "Parameters": [
            {
              "Id": 1292301,
              "Level": 1,
              "Parameters": [
                9,
                6,
                18
              ]
            }
          ],
          "Display": 0
        },
        "Id": 1292301,
        "Name": "Когда находит настроение",
        "Description": "После применения элементального навыка <color=#FFD780FF>Непредвиденный удар</color> Лоэн на 9 сек. наделяется эффектом Душевного подъёма: уровень элементального навыка <color=#FFD780FF>Непредвиденный удар</color> повышается на 1.\nВо время использования элементального навыка, если уровень обычной атаки, элементального навыка или взрыва стихии другого персонажа отряда не ниже уровня элементального навыка Лоэна, то длительность данного Душевного подъёма дополнительно увеличивается на 6 сек.\nДушевный подъём можно получить один раз в 18 сек.",
        "Icon": "UI_Talent_S_Lohen_08"
      }
    ],
    "Talents": [
      {
        "Id": 1291,
        "Name": "О ветра, что несут скорбные песни",
        "Description": "Максимум {LINK#N11290004}<color=#FFD780FF>Жажды победы</color>{/LINK} Лоэна повышается до 300% от её исходного значения.\nКроме того, когда другие персонажи отряда поблизости наносят урон, а Лоэн находится в режиме {LINK#N11290001}<color=#FFD780FF>Мастерского хода</color>{/LINK}, количество предоставляемой ими <color=#FFD780FF>Жажды победы</color> повышается до 500% от исходного значения.",
        "Icon": "UI_Talent_S_Lohen_01"
      },
      {
        "Id": 1292,
        "Name": "В полёте я сражу всё, что летает",
        "Description": "Когда Лоэн находится в режиме {LINK#N11290001}<color=#FFD780FF>Мастерского хода</color>{/LINK}, на 4 сек. после того как особый элементальный навык {LINK#N11290002}<color=#FFD780FF>Врезано в кость и сердце</color>{/LINK} поражает врага или применяется взрыв стихии <color=#FFD780FF>Вынесение приговора</color>, он получает Истребляющий зло клинок: когда его последующая обычная или заряженная атака в режиме Мастерского хода поражает противника, он выполняет дополнительный удар, который наносит 500% <color=#99FFFFFF>Крио урона по площади</color> от силы атаки Лоэна, а также на 8 сек. мастерство стихий остальных персонажей отряда поблизости повышается на 200 ед. Истребляющий зло клинок может возникнуть один раз в 4 сек.",
        "Icon": "UI_Talent_S_Lohen_02"
      },
      {
        "Id": 1293,
        "Name": "Лишь копьё исцелит эту рану",
        "Description": "Увеличивает уровень навыка <color=#FFD780FF>{LINK#S11292}Непредвиденный удар{/LINK}</color> на 3.\nМакс. уровень: 15",
        "Icon": "UI_Talent_U_Lohen_01",
        "ExtraLevel": {
          "Index": 2,
          "Level": 3
        }
      },
      {
        "Id": 1294,
        "Name": "Лучезарная любовь, смеющаяся смерть",
        "Description": "Когда Лоэн применяет взрыв стихии <color=#FFD780FF>Вынесение приговора</color>, находясь в режиме {LINK#N11290001}<color=#FFD780FF>Мастерского хода</color>{/LINK}, его {LINK#N11290004}<color=#FFD780FF>Жажда победы</color>{/LINK} достигает предела, обеспечивая максимальное увеличение урона этого взрыва стихии.\n\nКроме того, когда Лоэн переходит в режим <color=#FFD780FF>Мастерского хода</color>, а его энергия:\n· Неполная: Лоэн восстанавливает 15 ед. энергии.\n· Полная: если в течение следующих 15 сек. Лоэн использует взрыв стихии <color=#FFD780FF>Вынесение приговора</color>, то он восстанавливает 15 ед. энергии.",
        "Icon": "UI_Talent_S_Lohen_03"
      },
      {
        "Id": 1295,
        "Name": "Не расспрашивай и не требуй ответа",
        "Description": "Увеличивает уровень навыка <color=#FFD780FF>{LINK#S11295}Вынесение приговора{/LINK}</color> на 3.\nМакс. уровень: 15",
        "Icon": "UI_Talent_U_Lohen_02",
        "ExtraLevel": {
          "Index": 9,
          "Level": 3
        }
      },
      {
        "Id": 1296,
        "Name": "Утонуть, погрузиться в забытьё - высшее блаженство",
        "Description": "Использование особого элементального навыка {LINK#N11290002}<color=#FFD780FF>Врезано в кость и сердце</color>{/LINK} и попадание им по противнику либо применение взрыва стихии <color=#FFD780FF>Вынесение приговора</color> в режиме {LINK#N11290001}<color=#FFD780FF>Мастерского хода</color>{/LINK} не расходует {LINK#N11290004}<color=#FFD780FF>Жажду победы</color>{/LINK}, а {LINK#N11290003}<color=#FFD780FF>Ликование</color>{/LINK} восстанавливается до предела. К тому же следующее применение особого элементального навыка <color=#FFD780FF>Врезано в кость и сердце</color> и попадание им по врагу увеличивает длительность текущего <color=#FFD780FF>Мастерского хода</color> на 1,25 сек. Эффект может возникнуть один раз в 7 сек.\nКроме того, крит. урон всего вышеописанного урона повышается на 175%, а максимальное количество применений навыка <color=#FFD780FF>Врезано в кость и сердце</color> в текущем режиме <color=#FFD780FF>Мастерского хода</color> Лоэна увеличивается на 2.",
        "Icon": "UI_Talent_S_Lohen_04"
      }
    ]
  },
  "FetterInfo": {
    "Title": "Заточенная стрела",
    "Detail": "Заместитель капитана отряда дальнего боя Ордо Фавониус, рыцарь, действующий нестандартно и предпочитающий необычные тактики.",
    "Association": 1,
    "Native": "Ордо Фавониус",
    "BirthMonth": 4,
    "BirthDay": 3,
    "VisionBefore": "Крио",
    "VisionOverrideUnlocked": "Глаз Бога",
    "ConstellationBefore": "Хитрый Заяц",
    "CvChinese": "林婧南",
    "CvJapanese": "天﨑滉平",
    "CvEnglish": "Nick Wolfhard",
    "CvKorean": "Lee Sang-ho",
    "CookBonus": {
      "OriginItemId": 108971,
      "ItemId": 108975,
      "InputList": [
        100016,
        100022,
        110006
      ]
    },
    "Fetters": [
      {
        "Title": "Привет...",
        "Context": "Приятно познакомиться. Я Лоэн, действующий заместитель капитана пятого отряда. Если вам требуется помощь Ордо Фавониус, обращайтесь напрямую в орден. Если же вам нужна моя личная помощь, то слушаю."
      },
      {
        "Title": "Поболтаем: Заместитель капитана",
        "Context": "Чтобы стать капитаном, одной силы мало. Главное - это... Хех, сам пока не знаю. Знал бы - уже был бы капитаном."
      },
      {
        "Title": "Поболтаем: Куда возвращается ветер",
        "Context": "Фух... В Мондштадте всё же комфортнее всего. Надо бы раздобыть яблочного сидра..."
      },
      {
        "Title": "Поболтаем: Взаимоотношения",
        "Context": "Как у меня складываются отношения с остальными в ордене? Хм... По крайней мере, я всем запомнился, так что это уже неплохо."
      },
      {
        "Title": "Когда идёт дождь...",
        "Context": "Ого, дождь усиливается. Интересно, сколько всего он смоет на этот раз?"
      },
      {
        "Title": "После дождя...",
        "Context": "Небо проясняется... будто и не было никакого ливня."
      },
      {
        "Title": "Когда гремит гром...",
        "Context": "Раскаты грома могут заглушить многое, но они точно не заглушат биение твоего собственного сердца."
      },
      {
        "Title": "Когда идёт снег...",
        "Context": "Я очень люблю таверну «Кошкин хвост»... особенно в такую погоду."
      },
      {
        "Title": "Когда дует ветер...",
        "Context": "Фух, ветер усиливается... Жаль, одуванчиков нет. Если рвать бумагу, эффект почти тот же, да?"
      },
      {
        "Title": "В пустыне...",
        "Context": "В такие моменты особенно скучаю по Сидровому озеру."
      },
      {
        "Title": "Доброе утро...",
        "Context": "Доброе утро. Чем сегодня будешь заниматься?"
      },
      {
        "Title": "Добрый день...",
        "Context": "#Уже пообедал{F#а}? Отлично - днём ещё много дел."
      },
      {
        "Title": "Добрый вечер...",
        "Context": "Сегодня вечером... Хм, устроим для отряда «учебную атаку на лагерь»."
      },
      {
        "Title": "Спокойной ночи...",
        "Context": "Спокойной ночи. Отдохни как следует. Завтра всё равно наступит, хочешь ты этого или нет."
      },
      {
        "Title": "О Лоэне: Отношение к боли",
        "Context": "Я стараюсь избегать обезболивающих - они мешают сражаться. Да и... Хех, мне даже нравится чувствовать боль. Это напоминает, что я жив. В отличие от моих врагов."
      },
      {
        "Title": "О Лоэне: Сила и оправдания",
        "Context": "Для некоторых «сила» - удобное оправдание. Ею объясняют неудачи, страхи, сомнения... Наверное, наличие чёткой цели действительно дарит людям странное чувство защищённости. Даже если за этой «защищённостью» скрывается нечто ужасное."
      },
      {
        "Title": "О нас: Стиль боя",
        "Context": "Мой стиль боя? Ха-ха! Всё просто: найти главного, вступить в бой и как можно быстрее определить победителя. Остальные рыцари уже должны были привыкнуть. А если нет - это их проблемы."
      },
      {
        "Title": "О нас: Долг службы",
        "Context": "Как видишь, я уже заместитель капитана, а Теодор понёс заслуженное наказание. Но его способности ещё пригодятся. Когда он искупит вину, я верну его в пятый отряд. Правда, уже не в качестве заместителя. И доверять ему - как и мне - пока рано.\nТы веришь мне? И у тебя есть сила, чтобы верить? Ха-ха! Достойно почётного рыцаря. Может, тогда сразу станешь капитаном нашего пятого отряда? Варка точно не будет возражать."
      },
      {
        "Title": "Глаз Бога...",
        "Context": "Глаз Бога отлично помогает в бою. Жаль только, что он эффективен лишь против тех врагов, до которых можно дотянуться, но не против тех, что скрываются внутри."
      },
      {
        "Title": "Давай поделимся...",
        "Context": "Я не пью. Алкоголь мне нужен только для дезинфекции ран. Старое вино из одуванчиков винокурни «Рассвет» подходит идеально: и обеззараживает, и жжёт как следует. А заодно можно посмотреть, как корчатся другие, когда я обрабатываю их раны алкоголем. Особенно Варка. Хе-хе."
      },
      {
        "Title": "Интересные вещи...",
        "Context": "Раньше у меня была аллергия на одуванчики. Сахароза посоветовала «десенсибилизацию». Я заполнил комнату одуванчиками и периодически вдыхал их пыльцу. Помогло ли? Теперь я не чихаю. Хотя, признаться, иногда скучаю по прежним временам."
      },
      {
        "Title": "О Варке: Стойкость к лекарствам",
        "Context": "С каждым днём Варка становится всё устойчивее к лекарствам. Недавно приготовленный мной настой едва вызвал у него румянец. Если бы он потом не посмотрел на меня так, я бы решил, что вообще ничего туда не добавил. Эх... Будь мы сейчас в Нод-Крае, я бы подмешал кое-какие растения, обладающие силой куувяки."
      },
      {
        "Title": "О Варке: Обязанности магистра",
        "Context": "Обязанности магистра? Варка в основном ведёт людей в бой. Всё остальное достаётся Джинн. Ха-ха. Врагов можно уничтожить, а вот бумажная работа бесконечна."
      },
      {
        "Title": "О Джинн...",
        "Context": "Пока действующий магистр руководила всем в Мондштадте, магистр ордена мог спокойно разгуливать по Нод-Краю. Теперь он вернулся. Ну, думаю, всё останется как прежде - будет делать что захочет."
      },
      {
        "Title": "О Кэйе...",
        "Context": "У Кэйи настоящий талант к подделке подписей капитанов, и особенно подписи Джинн. Он это делает настолько идеально, что отличить подделку почти невозможно. Сам он говорит, что делает это только для того, чтобы подписывать себе отгулы. Честно говоря, я ему верю. Уж слишком он правильный, ха-ха."
      },
      {
        "Title": "Об Эмбер...",
        "Context": "Эмбер говорила, что уже всё обсудила с действующим магистром Джинн. К ней направят разведчиков на помощь - пусть и не официальных скаутов. Это хорошо: теперь ей не придётся в одиночку летать над всем Мондштадтом. Хотя, если подумать, экзамен на лётную лицензию тоже уже устарел. Может, его пора обновить?"
      },
      {
        "Title": "О Дилюке...",
        "Context": "Дилюк... Если подумать, мы оба пострадали от одного и того же негодяя. Теперь, когда с этим покончено, неужели он так и не вернётся в Ордо Фавониус? Самым молодым капитаном ему уже не стать, но вот самым старшим рыцарем - вполне."
      },
      {
        "Title": "О Ноэлль...",
        "Context": "Ноэлль всё ещё не стала полноценным рыцарем, да? Сколько уже времени прошло... Я был уверен, что она давно прошла отбор. Может, Варка готовит для неё какое-то особое испытание? Тогда и титул у неё должен быть под стать - длинный, как её путь."
      },
      {
        "Title": "Об Эоле...",
        "Context": "Первое, что приходит на ум, когда думаешь об Эоле, - это звук её шагов. Стоит ей ускориться, как её «топ-топ-топ» слышно даже этажом ниже. Прямо как её стиль боя - громкий, пронзительный, незабываемый."
      },
      {
        "Title": "Об Альбедо...",
        "Context": "Всё расходное снаряжение пятого отряда разрабатывается Альбедо и восьмым отрядом. Болты для арбалетов, пули, алхимические смеси - всё на высшем уровне. Я иногда заглядываю к Альбедо с идеями для нового оружия, но в последнее время всеми делами занимается Сахароза. Альбедо снова ушёл с головой в какой-то крупный проект."
      },
      {
        "Title": "О Кли...",
        "Context": "Варка как-то сказал, что Предвестник Фатуи, Капитан, способен уничтожить стража руин обычным восковым мелком. Я обменял у Кли коробку мелков на сладости и собираюсь отдать Варке. В следующий раз, когда он столкнётся с монстром, проверим, насколько его утверждение является правдой."
      },
      {
        "Title": "О Мике...",
        "Context": "Мика - отличный картограф, но я ещё лучше умею распознавать ложь. Однажды он специально не отметил на карте места скопления монстров, чтобы я не рванул туда в одиночку. Но стоило мне взглянуть на его лицо - и я сразу понял, где они. Наивно думать, что молчание может меня остановить."
      },
      {
        "Title": "Узнать больше о Лоэне I",
        "Context": "Прости. Не хочу разочаровывать, но у меня нет никаких тёмных и мрачных секретов."
      },
      {
        "Title": "Узнать больше о Лоэне II",
        "Context": "Хотя я чаще пользуюсь копьём, я рыцарь пятого отряда, поэтому не забрасываю тренировки с арбалетом и мушкетом. С меткостью у меня всё в порядке - по слаймам и прочей мелочи попадаю без проблем. Говорят, в Инадзуме есть духи, по которым трудно попасть? Надо будет проверить."
      },
      {
        "Title": "Узнать больше о Лоэне III",
        "Context": "Пятый отряд? Обычная группа огневой поддержки на расстоянии, ничего особенного. Огневой мощи хватает, но против по-настоящему опасных противников мы можем только прикрывать со стороны. Как тогда, когда мы сопровождали Варку при перехвате Лунного мстителя: в итоге он вёл основной бой, а нам приказали держать периметр и сдерживать Дикую Охоту, иначе нас бы просто смели."
      },
      {
        "Title": "Узнать больше о Лоэне IV",
        "Context": "Почему я использую копьё? Всё просто: лучшая приманка на поле боя - тот, кто выглядит как командир. Я отвлекаю врагов, а остальные спокойно ведут огонь. А что до опасных противников... Ха-ха, чем напряжённее ситуация, тем легче мне сосредоточиться. Это ощущение - настоящее удовольствие. Жаль только, после Нод-Края таких боёв стало слишком мало."
      },
      {
        "Title": "Узнать больше о Лоэне V",
        "Context": "Боюсь ли я ближнего боя? Ха! Не больше, чем мой противник. Я не из тех, кто сдаётся. К тому же у меня за спиной врачи. А если они есть и у врага? Тогда я сначала разберусь с ними."
      },
      {
        "Title": "Хобби Лоэна...",
        "Context": "Помимо сражений, моё любимое занятие - подбрасывать товарищам небольшие «сюрпризы», чтобы разбавить их скучную жизнь. Это тоже часть тренировок: рыцарь должен быть начеку всегда."
      },
      {
        "Title": "Беспокойство Лоэна...",
        "Context": "Хорошие времена в Терновом порту закончились. Теперь я снова в Мондштадте, а действующий магистр Джинн куда строже, чем Варка. Эх... Неужели нельзя отправить меня ещё в пару командировок?"
      },
      {
        "Title": "Любимая еда...",
        "Context": "Я люблю острую еду. На дежурстве часто жую сушёный заоблачный перец. Он отлично бодрит. Его называют «заоблачным перчиком»? Спасибо, но для меня это просто перец."
      },
      {
        "Title": "Нелюбимая еда...",
        "Context": "Не пей алкоголь, ладно? В Нод-Крае меня постоянно будили пьяные рыцари. Под конец они уже не понимали, что пьют, даже когда я подменял им выпивку на... Хм, забудь."
      },
      {
        "Title": "Подарок I",
        "Context": "#Фух! Спасибо, это как раз мне по вкусу. Настолько подходит... что я начинаю подозревать, не изучал{F#а} ли ты мои привычки. Но ничего, у меня тоже есть кое-какая информация о тебе."
      },
      {
        "Title": "Подарок II",
        "Context": "#Когда я учился подмешивать яд в еду, довёл это до совершенства - никто ничего не замечал... Ты уже подмешал{F#а} яд? Не переживай, у меня высокая устойчивость. Думаю, съем ещё."
      },
      {
        "Title": "Подарок III",
        "Context": "...Ну уж нет, слишком уж очевидная ловушка. В такую я не полезу. В следующий раз готовлю я."
      },
      {
        "Title": "День рождения...",
        "Context": "Сегодня у тебя день рождения, так что я принёс подарок - мини-арбалет. Сам разработал. По размеру должен идеально подойти к запястью... Когда успел измерить? На глаз. Можешь доверять. Я всё-таки заместитель капитана пятого отряда. Ах да, он ещё и назад стреляет - на случай, если кто-то подкрадётся сзади. Нужно лишь нажать... вот здесь. Ха-ха, не пригибайся! Предохранитель всё ещё включён. Я что, похож на человека, который дарит другу арбалет, чтобы потом посмотреть, как тот сам себя застрелит?"
      },
      {
        "Title": "Чувство возвышения: Начало",
        "Context": "Чувствую себя отлично. Даже оружие в руках словно легче стало."
      },
      {
        "Title": "Чувство возвышения: Нарастание",
        "Context": "Кажется, я теперь вижу дальше... Это точно поможет мне целиться точнее."
      },
      {
        "Title": "Чувство возвышения: Кульминация",
        "Context": "Голова стала яснее. Ха, уже придумал новый способ тренировки."
      },
      {
        "Title": "Чувство возвышения: Окончание",
        "Context": "Моей силы теперь достаточно, чтобы стать «образцовым» заместителем капитана?"
      },
      {
        "Title": "Элементальный навык I",
        "Context": "В бой!"
      },
      {
        "Title": "Элементальный навык II",
        "Context": "Пощады не будет."
      },
      {
        "Title": "Элементальный навык III",
        "Context": "Никого не оставлять в живых!"
      },
      {
        "Title": "Элементальный навык IV",
        "Context": "Неожиданно?"
      },
      {
        "Title": "Элементальный навык V",
        "Context": "Сейчас наш шанс!"
      },
      {
        "Title": "Элементальный навык VI",
        "Context": "Гм."
      },
      {
        "Title": "Взрыв стихии I",
        "Context": "Как агнцы на заклание."
      },
      {
        "Title": "Взрыв стихии II",
        "Context": "Сопротивление бесполезно!"
      },
      {
        "Title": "Взрыв стихии III",
        "Context": "Ха-ха, сказки с хорошим концом - не про тебя!"
      },
      {
        "Title": "Открытие сундука I",
        "Context": "Так, трофеи... Посмотрим, что тут у нас."
      },
      {
        "Title": "Открытие сундука II",
        "Context": "Негусто... но не брать было бы невежливо."
      },
      {
        "Title": "Открытие сундука III",
        "Context": "Хм, ни ловушек, ни ядовитого дыма... Скучно."
      },
      {
        "Title": "Низкий уровень HP I",
        "Context": "Ха... Давай ещё!"
      },
      {
        "Title": "Низкий уровень HP II",
        "Context": "...Это ещё не конец!"
      },
      {
        "Title": "Низкий уровень HP III",
        "Context": "Отличный противник!"
      },
      {
        "Title": "Низкий уровень HP компаньона I",
        "Context": "Если не справляешься - отходи!"
      },
      {
        "Title": "Низкий уровень HP компаньона II",
        "Context": "Дай мне попробовать!"
      },
      {
        "Title": "Без сознания I",
        "Context": "Вот он... предел возможностей..."
      },
      {
        "Title": "Без сознания II",
        "Context": "Мне всё ещё... мало..."
      },
      {
        "Title": "Без сознания III",
        "Context": "Ветер... скажи мне почему..."
      },
      {
        "Title": "Получен лёгкий удар I",
        "Context": "Дешёвый приём."
      },
      {
        "Title": "Получен лёгкий удар II",
        "Context": "Я даже не почувствовал."
      },
      {
        "Title": "Получен тяжёлый удар I",
        "Context": "Неплохо..."
      },
      {
        "Title": "Получен тяжёлый удар II",
        "Context": "Ах!.."
      },
      {
        "Title": "Присоединяется к группе I",
        "Context": "Пошли, разомнёмся."
      },
      {
        "Title": "Присоединяется к группе II",
        "Context": "Возглавить авангард? Без проблем."
      },
      {
        "Title": "Присоединяется к группе III",
        "Context": "На этот раз я прикрою тыл."
      }
    ],
    "FetterStories": [
      {
        "Title": "О персонаже",
        "Context": "Едва экспедиционный корпус отправился в обратный путь, как барды уже начали рассказывать в тавернах истории о его героях.\nНаряду с такими знакомыми именами, как Варка, в поле зрения общественности попало и новое звание - офицер по подавлению фронта, которое присваивалось за выдающиеся заслуги и исключительно высокую активность в боях.\nПочему стрелковое подразделение, призванное сражаться на максимальном расстоянии, всегда действовало на передовой, а порой даже возглавляло наступление и атаковало первыми?\nПочему отряд, вооружённый луками, арбалетами и мушкетами, возглавляет молодой рыцарь с копьём в руках?\nТакое несоответствие не могло не вызвать вопросов, а где возникают вопросы, там вскоре начинаются споры.\nНекоторые возмущались: «Разве стрельба с близкого расстояния может быть неэффективной? Неужели лук, арбалет и мушкет настолько неудобны в обращении?»\nДругие утверждали, что лучники всегда были одними из самых сильных солдат и отправлять лучших воинов на опасные передовые позиции было лучшим решением.\nВ итоге, рассказы бардов, основанные на свидетельствах очевидцев, положили конец спорам:\n«Он - самое острое копьё отряда, способное прорвать любую линию обороны;\nон - самый крепкий щит отряда, способный остановить любой натиск...»\nОднако барды часто намеренно упускают вторую половину слов рыцарей, потому что в них нет легендарного колорита, они слишком уж прозаичны:\n«Я думаю, что заместитель капитана Лоэн считает, что так эффективнее...»\nДа, в его истории нет ни той славы и величия, что присущи легендам о рыцарях, ни тех драматических поворотов, которые характерны для героических сказаний.\nКопья, выпущенные тайком стрелы, засады, яд, внезапные атаки, диверсии...\nОн никогда не спорит о том, какое оружие или какая тактика лучше, и не задумывается о том, что принесёт ему сражение или задание, - честь или позор.\nКаждый из этих методов вызывает разные ощущения, но ни одно из них не сравнится с радостью победы и с обычным ощущением того, что ты жив.\nТолько тот, кто выстоял, имеет право размышлять о смысле победы. Только тот, кто способен чувствовать боль, имеет право говорить о выживании.\nСражаться, побеждать, выживать... И так по кругу...\nЭто история Лоэна, его жизнь..."
      },
      {
        "Title": "История персонажа 1",
        "Context": "В воспоминаниях Лоэна его первой игрушкой был маленький мягкий лук.\nЕго строгий, неулыбчивый отец выбрал лучшую сердцевину пихты для корпуса лука, а заботливая и внимательная мать тщательно выкроила кожу, раз за разом разминая и скручивая её, чтобы сделать тетиву.\nЭто была обычная игрушка, но родители изготовили её, следуя тем же методам изготовления луков, которые они применяли в своей повседневной работе, и проявили при этом предельную скрупулёзность.\nОднако отец не стал учить маленького Лоэна натягивать тетиву и вставлять стрелу, как тот ожидал.\nЕдинственное, что ему разрешалось, - это подражать родителям: он учился осматривать плечо лука, смазывать и ухаживать за лакированной поверхностью, а также натирать воском тетиву. День за днём, снова и снова.\n«Лоэн, наши предки однажды сказали, что лук - это орудие, требующее постоянства. На протяжении многих поколений наша семья зарабатывала на жизнь изготовлением луков. Соответственно, мы должны жить так же, как они, и следить за тем, чтобы всё, что мы делаем, отличалось безупречным постоянством».\nВо время ежедневной утренней молитвы отец и мать Лоэна всегда повторяли эти слова.\nРазмеренный распорядок дня, усердный труд и спокойная жизнь.\nОни прожили так более двадцати лет до рождения Лоэна. И через десять с лишним лет после его рождения ничто не изменилось.\nОт первого лепета до умения ловко ухаживать за луком и стрелами Лоэн внезапно осознал, что уже словно видит весь свой жизненный путь. Возможно, он будет идти по нему до тех пор, пока старость не притупит его зрение, а текстура дерева не станет неразличимой, пока его жизнь не износится в тишине неизменной рутины.\nСтрелы можно бережно хранить в оружейной, но они не созданы для того, чтобы оставаться там навечно. Точно так же его неукротимый нрав не был создан для спокойной и умиротворённой жизни.\nМаленький Лоэн в очередной раз отполировал наконечник стрелы до блеска и посмотрел на свои тёмно-красные зрачки в его отражении.\nСтрела ждёт момента, когда сорвётся с тетивы...\nИ этот момент был не за горами.\nВ самый обычный день Лоэн, как всегда, сидел в повозке, сопровождая отца в поездке в Мондштадт, чтобы доставить заказ.\nНо на этот раз поездка была отнюдь не спокойной. Группа хорошо подготовленных бандитов в масках нацелилась на их груз.\nОтец поспешно затолкнул Лоэна в крытую повозку, приказав ему не шевелиться и не издавать ни звука. Затем он громко закричал, пытаясь то ли отвлечь бандитов, то ли позвать на помощь рыцарей ордена, где бы они ни находились.\nХотя повозка была загружена мощными луками и стрелами, способными пробить даже камень...\nХотя его отец, благодаря многолетнему опыту проверки луков, приобрёл навыки первоклассного лучника...\nБандиты, казалось, то намеренно, то будто невзначай пытались оттеснить его от повозки...\nМноголетняя привычка к спокойной жизни заставила отца Лоэна полностью забыть о том, что нужно проявлять настороженность, и даже мысль защищаться с помощью силы не пришла ему в голову.\nВскоре звуки снаружи затихли. Через некоторое время полог откинулся, но за ним оказался не его отец, отбивший нападение бандитов, и не подкрепление из ордена, а несколько фигур в чёрных одеждах и масках.\nНе произнеся ни слова, они схватили Лоэна и унесли его. Он пытался сопротивляться и вырываться, но все его усилия были тщетны - руки, которые держали его, были тверды, как железо.\nВ тот момент Лоэн ещё не знал, в чью интригу он оказался втянут и куда его везут.\nВ тесной, тёмной клетке юный Лоэн сидел в тишине, снова и снова обдумывая одну мысль.\nЕсли бы отец поднял лук и встал на пути у бандитов, они бы ни за что не напали на них. А если бы он сам был быстрее и сообразительнее... Возможно, ему удалось бы ускользнуть прежде, чем его схватили.\nПлач других похищенных детей в соседней клетке становился всё громче. Лоэн, воспользовавшись моментом, когда никто на него не смотрел, спрятал в рукав наконечник стрелы, который захватил с собой из повозки...\nВозможно, Анемо Архонт услышал отчаянные мольбы детей о помощи, а может, некая невидимая сила ответила на молчаливое стремление мальчика обрести силу.\nПока злодеи спешили увести своих пленников, наконец-то появились стражи порядка.\nВо главе их стояла одинокая фигура в доспехах с лёгким луком в руке. С непринуждённой точностью он уничтожал злодеев.\nСтремясь не ранить их, чтобы потом допросить или же чтобы не причинить вреда детям, он пускал только тупые, незаточенные стрелы.\nИ всё же в его руках даже затупленные стрелы поражали словно гром. Каждый выстрел разрывал воздух; на каждый удар отвечал глухой стук падающего тела.\nСтрелы пронзали воздух с такой яркостью, с такой неукротимой силой, что Лоэн не мог отвести взгляд. Его руки, застывшие в движении, словно окаменели.\nМальчик вышел из оцепенения, только когда Адорно приоткрыл занавес тюремной повозки и встретил взгляд Лоэна.\n«Если бы я обладал такой же силой, как те стрелы... Я бы давно перерезал эти веревки. И мне не пришлось бы столько времени слушать плач Теодора...»\nЭта мысль незаметно пустила корни в сердце маленького Лоэна.\nА Адорно увидел совсем другую картину.\nНа фоне плачущих детей выделялся один мальчик. Его лицо было непроницаемым, взгляд - твёрдым, и он не поддался панике.\nТуго завязанная на его запястьях верёвка была надрезана - ровно настолько, чтобы стало видно едва заметный, аккуратный след от припрятанного наконечника стрелы.\n- Какой необыкновенный ребёнок... Надо будет за ним понаблюдать."
      },
      {
        "Title": "История персонажа 2",
        "Context": "С тех пор как Лоэна спасли, его семья стала гораздо внимательнее следить за ним, боясь, что он снова может пропасть. Но когда тетива натянута, стрела уже не может вернуться к жизни, покрытой пылью обыденности.\nОднажды лунной ночью, когда родители спали, Лоэн тихонько выскользнул в окно. Вместе с ним в темноту погрузились самодельный короткий лук, маленький нож для резьбы и несколько бракованных стрел, не соответствующих стандартам качества.\nМожет, это была удача, а может, он был создан для этого, но когда Лоэн вернулся, в его рюкзаке лежали два наконечника стрел хиличурлов - его трофеи.\nС тех пор он начал всё чаще выбираться из дома по ночам. Сначала раз в неделю, потом раз в три дня, а затем и каждую ночь. Его противники становились всё сильнее, а трофеи - всё разнообразнее: разбитые маски, зловещие свитки, рога митачурлов...\nСо временем среди искателей приключений начали распространяться слухи, что в полночь в окрестностях Тернового порта появляется невысокий худощавый лучник. Он словно ураган врывается в толпу монстров и точным выстрелом поражает всех до единого.\nПобеды следовали одна за другой, но вместе с ними приходила и опасность. И каждое столкновение с ней заставляло сердце Лоэна биться всё быстрее.\nГде-то на этом пути в его голове зародился вопрос: если он снова столкнётся с теми нападавшими... что будет? Он по-прежнему беспомощный ребёнок, который ждёт, что его спасут?\nОн преодолел множество опасностей и сразил бесчисленное количество противников, но этот вопрос не давал ему покоя. С годами он становился ещё более насущным, нарастая и будоража душу Лоэна, и не находил ответа.\nЕдинственный выход - пронзить ту самую цель, с которой всё началось.\n...\nКогда Лоэн официально надел форму искателя приключений и признался родителям, они сначала замерли от удивления, а потом пришли в ярость.\nВ конце концов вмешался Сайрус и уверенно заявил, ударяя себя в грудь, что это Лоэн будет изводить монстров, а не наоборот. Лишь тогда они с неохотой смирились с тем, что изменить уже было невозможно.\n...Они признали не силу Лоэна, а тот факт, что он больше никогда не будет послушным ребёнком, каким они его знали.\nОднако они не могли с этим смириться. На протяжении многих лет они пытались убедить его перестать рисковать жизнью, даже обратились к Адорно, опытному рыцарю, который когда-то спас Лоэна, в надежде, что тот вразумит его.\n«Когда тетива натянута, стрела уже не может вернуться к прежней жизни. Вы мастера луков и должны понимать это», - Адорно, казалось, давно ожидал, когда Лоэн сделает свой выбор. - Но мы можем придать ей нужное направление. Вот мой совет как лучника».\nАдорно согласился выступить в роли посредника. Родители Лоэна так и не узнали, о чём они говорили, но в следующие несколько месяцев Лоэн стал вести себя гораздо спокойнее... по-видимому «готовился к экзаменам».\nСпустя несколько месяцев Лоэн неожиданно появился на отборочных испытаниях Ордо Фавониус и, продемонстрировав потрясающее мастерство, занял первое место. Его методы вызывали неоднозначную реакцию, но в итоге ему удалось вступить в орден.\nПо крайней мере, в рядах рыцарей у него была официальная должность и товарищи, на которых можно положиться. Это лучше, чем быть одиноким искателем приключений.\nК тому же несколько месяцев назад Лоэну стали надоедать скучные поручения Гильдии искателей приключений, и он подумывал покинуть Мондштадт в поисках более опасных противников.\nРодители Лоэна поддерживали друг друга, но не могли избавиться от одного навязчивого сомнения: что именно сказал Адорно в тот день, что заставило Лоэна принять решение вступить в Ордо Фавониус? Чем больше они об этом думали, тем больше терялись в догадках.\n...\n«...Парень, мы установили личность главного организатора тех похищений».\nЛоэн, который до этого не проявлял особого интереса к очередному посреднику, внезапно пристально посмотрел на него: «Кто это?»\n«Ордо Фавониус скоро опубликует объявление, но можешь забыть о мести», - спокойно произнёс Адорно. - Он уже мёртв».\nПосле долгого молчания Лоэн снова заговорил: «Кто убил его?»\n«Самоубийство». «Такой человек не мог покончить с собой. Ты знаешь, о чём я спрашиваю: кто загнал его в угол?»\nАдорно едва заметно улыбнулся: «Наш магистр ордена, Рыцарь Бореалис, живая легенда Мондштадта... Достойная цель, так ведь?»"
      },
      {
        "Title": "История персонажа 3",
        "Context": "Варка давно привык к «подражателям».\nДля энергичных молодых людей вполне естественно стремиться следовать по стопам великого героя. И среди них всегда найдутся самоуверенные задиры.\nНо такого «подражателя», как Лоэн, Варка видел впервые.\nПрежние «подражатели» могли, в лучшем случае, устроить неожиданную засаду, как правило, лишь для того, чтобы продемонстрировать собственную силу. Но дебют Лоэна можно охарактеризовать единственно как... необузданный.\nСтрелы из засады, дымовые завесы, ловушки, даже снотворные препараты, способные мгновенно вывести монстров из строя, - его методы были отточены до нечеловеческого совершенства. В них чувствовалась рука ветерана, закалённого бесчисленными сражениями, и в них можно было уловить слабые отголоски наследия Эроха.\n«Неплохо, паренёк. У тебя есть способности! Но эти дешёвые трюки на меня не действуют!»\nВ мгновение ока Варка обездвижил «паренька».\n«Ребёнок, который сохранил хладнокровие, когда его похитили, и, возможно, даже смог бы сбежать без посторонней помощи».\n«Худощавый лучник, о котором ходят слухи. Тот, что наносит удары с безжалостной точностью в окрестностях Тернового порта».\n«Молодой горячий новобранец, который вскоре после поступления на службу начал преследовать остатки фракции Эроха».\nОн слышал от Адорно немало историй о Лоэне. Поэтому решил проследить за развитием этой маленькой комедии ещё некоторое время, чтобы понять, из чего на самом деле сделан этот парень.\nКакое выражение появится на лице этого неопытного новичка под сокрушительным давлением двух гигантских мечей, способных заставить замереть даже полчища демонов?\nВосхищение? Растерянность? Или?..\nВарка пристально посмотрел в глаза Лоэна. Холодный взгляд. Непоколебимый. С каждой секундой он становился всё жёстче. И в этом взгляде он как будто уловил что-то. Проблеск восторга... и, пожалуй, себя в молодости, без колебаний стремившегося к силе и славе.\nМногообещающий талант, но ему нужно было пройти школу жизни. Ему предстояло набить шишки и научиться всему на собственном горьком опыте. Поэтому Варка взял дело в свои руки, усмирил дерзкого новичка и приказал запереть его в камере на несколько дней. «Если ты не согласен, можешь попробовать снова в любое время. Буду с нетерпением ждать».\n«Подожди и увидишь», - Лоэн улыбнулся и пожал плечами, после чего отправился в камеру.\nНа следующий день после окончания своего заключения Лоэн появился у двери Варки с бутылкой его любимого вина, заявив, что это извинение.\n«О? Ты и впрямь всё понял, даже выбрал моё любимое вино из одуванчиков. С радостью приму его».\nЕдва острая, горькая жидкость коснулась его горла, магистр ордена почувствовал лёгкое головокружение - что-то было не так. Затем в его памяти всплыли слова, которые Адорно сказал ему после того, как Лоэна заключили под стражу:\n«Честно говоря, я не советую тебе видеть в нём себя прежнего или любого другого ребёнка из Мондштадта, который восхищается тобой. Да, Лоэн восхищается твоей силой, но я полагаю, что больше всего он размышляет о том, как бросить тебе вызов».\n«Если я не ошибаюсь, он думает так: попытаться бросить вызов самому \"могущественному Варке\" - это само по себе интересно. Даже если проиграю, ничего страшного, в худшем случае придётся пару дней полежать в постели. Что касается славы и тому подобного, думаю, его это не особо волнует».\nТолько благодаря могучему телосложению и силе воли Варка смог устоять на ногах под ошеломлённым взглядом Лоэна.\n«...Невероятно, по моим расчётам, этой дозы хватило бы, чтобы свалить десяток лесных кабанов...»\n«Парень, я же говорил, что такие дешёвые трюки на меня не действуют!»\nС этого момента у Лоэна появилось совершенно новое понимание слова «сила».\nЭто было нечто, с чем не могли справиться ни ловушки, ни яд - стойкость, закалённая бесчисленными столкновениями со смертью, и незыблемый фундамент, сформированный временем.\nС тех пор в списке целей Лоэна появилось ещё два пункта.\nПервое: любыми способами одолеть Варку.\nВторое: использовать все эти методы на себе и выстоять."
      },
      {
        "Title": "История персонажа 4",
        "Context": "Ордо Фавониус - это организация с богатой и славной историей, которая дала миру бесчисленное множество героев и пережила столько же трагедий и испытаний.\nОпираясь на эти легенды и уроки, извлеченные из тяжёлого опыта, рыцари пришли к пониманию одной простой истины.\nКогда действия нарушают рыцарский кодекс, трагедия не заставляет себя долго ждать.\nИменно по этой причине среди рыцарей ордена начали возникать сомнения по поводу назначения Лоэна заместителем капитана пятого отряда.\nБезумцу, известному тем, что он доставляет неприятности, устраивает засады на магистра ордена и в бою предпочитает яд и ловушки, вряд ли можно было приписать хоть что-то, напоминающее идеалы рыцарства.\nЛоэн, со своей стороны, не придавал этим слухам особого значения.\n«Я знаю, тебе плевать на чужое мнение, - сказал Адорно, - но ты же понимаешь, что экспедицию невозможно осуществить в одиночку. Если никто не захочет поддержать тебя, твою заявку на участие в экспедиции... вряд ли одобрят».\nОн замолчал, возможно, опасаясь, что Лоэн не сможет справиться с ситуацией, а может быть, боясь, что усугубит дело.\nС тех пор как Варка объявил о беспрецедентной грандиозной экспедиции, Лоэн с нетерпением ждал возможности присоединиться к ней.\nДалёкое поле боя, неизвестные опасности - всё это привлекало его больше всего на свете. И всё же его заявка встречала один отказ за другим. Один за другим публиковались списки отобранных кандидатов, но его имени в них не значилось.\nАдорно знал, что никакое испытание на поле боя не сможет поставить Лоэна в тупик. Значит, проблема крылась в другом.\nНо на этот раз Лоэн был на удивление спокоен: «Ну ладно, раз нестандартному рыцарю не разрешают участвовать в отборочных испытаниях, значит, я стану экзаменатором».\n...\n«С практической точки зрения это неплохая идея. Возможно, это также напомнит рыцарям об их собственных недостатках и заставит замолчать тех, кто постоянно ставит под сомнение необходимость реформ. Нельзя ожидать, что противник будет строго следовать рыцарскому кодексу».\nВарка пролистал весьма нетрадиционное «заявление» Лоэна и задумался над этим предложением.\nВ отчёте был перечислен целый ряд «испытаний». Помимо привычных ночных рейдов, ловушек и ядов - методов, к которым Варка уже давно привык, - в нём также фигурировали более изобретательные подходы: засады в маскировке, диверсии на линиях снабжения перед учениями и другие нестандартные «методы оценки».\nВ конце отчета Лоэн даже вставил одну знаменитую цитату, от которой Варка чуть не подавился вином.\n«Если рыцари Ордо Фавониус не могут защитить себя, как они защитят Мондштадт?» Фраза, сказанная в ночь нападения на предыдущего магистра ордена.\n...Ошибки молодости имеют свойство настигать человека, когда он меньше всего этого ожидает. Собравшись с мыслями, Варка принял решение и поставил на заявлении свою подпись.\nНеобычным рыцарям нужны необычные «испытания».\nКак рыцарям экспедиции... так и самому Лоэну."
      },
      {
        "Title": "История персонажа 5",
        "Context": "Лоэн, который считается наиболее вероятным преемником титула Рыцарь милосердия, пожалуй, меньше других рыцарей Ордо Фавониус соответствует этому образу.\nВ представлении большинства людей Рыцарь милосердия призван спасать других из опасности, не давать им оказаться на грани гибели. Но Лоэн предпочитает искать опасность и при этом втягивать в неё других. Разумеется, под «другими» обычно подразумеваются его враги... и не всегда люди.\nВпрочем, эти его «привычки» имеют свои преимущества. По крайней мере, когда речь идёт о спецоперациях и заданиях с высоким уровнем риска, его результаты значительно превосходят ожидания.\nПо этой причине многие секретные задания экспедиции естественным образом легли на его плечи.\nОдна из таких задач поступила в виде конфиденциального запроса от нынешней главы Северной разведсети.\nСогласно разведданным, некий подпольный аукционный дом, пользуясь царящим в регионе хаосом, активно действует в Нод-Крае. Они занимаются контрабандой и торгуют опасными лотами. Действуют крайне осторожно, за их спиной наверняка стоит какая-то влиятельная сила. Если удастся от них избавиться, то так можно заслужить доверие Северной разведсети.\n«Мы ни капли не сомневаемся в боевой мощи рыцарей, но на территории, где не чтят рыцарских правил, боевая мощь не всегда равна истинной силе».\nЧтобы развеять сомнения Северной разведсети, экспедиционный корпус разработал весьма надёжный план:\nЛоэн должен был тайно захватить изолированных членов группировки и выведать время и место проведения аукциона; затем, посредством слежки, прослушивания и постепенной проверки, выявить причастных лиц и свести риски к минимуму.\nКак ни посмотри, это задание идеально подходило Лоэну: одиночное проникновение, точечный захват, прямой удар в самое сердце - достаточно сложно и достаточно скрытно.\nК сожалению, Нанина упустила одну деталь: для Лоэна слишком скрытный план часто означал недостаточно радикальный.\nПеред отъездом Нанина также передала наставление кардинала Шеймуса: «Сосредоточься на задании, не отвлекайся на посторонние дела».\nНа это Лоэн без колебаний ответил: «Не беспокойтесь, я всё понимаю».\nИ он действительно понимал.\nПо крайней мере, по его собственному разумению, с самого начала у этого задания был только один главный смысл - продемонстрировать могущество Ордо Фавониус Северной разведывательной сети.\n...\nНесколько дней спустя, Мондштадт, кабинет магистра ордена.\nДействующий магистр Джинн, ознакомившись с отчётом экспедиционного корпуса, берёт перо, чтобы написать ответное письмо Варке.\n«Относительно операции с подпольным аукционом мне теперь известна полная картина.\nЛоэн в очередной раз продемонстрировал эффективность и решительность в принятии решений на месте. Он успешно удержал всех участников на месте и не допустил распространения боя на Нашгород, в результате чего среди мирных жителей никто не пострадал. Если судить исключительно по результату, это действительно можно назвать защитой народа и воплощением милосердия.\nЕсли судить по заслугам, я согласна с вашей оценкой: теперь он достоин унаследовать дело господина Адорно. Его действия были взвешенными и продуманными... вплоть до момента проникновения на вражескую базу.\nОднако, позвольте заметить: появление в центре вражеского опорного пункта, провокация боя по собственной инициативе, прорыв в одиночку и даже демонстрация трофеев для хвастовства силой - это отнюдь не стандартная тактика Ордо Фавониус.\nЕсли у вас найдётся время, пожалуйста, обязательно разъясните это сотрудникам Северной разведывательной сети»."
      },
      {
        "Title": "Псевдо-интегрированное устройство для записи переговоров",
        "Context": "«Интегрированное устройство для картографирования местности», которое Мика всегда носит с собой, неизменно содержится в образцовом порядке.\nВ нём не только записаны подробные данные о рельефе, ключевых точках и стандартных маршрутах передвижения, но иногда добавляются сведения о следах активности монстров и оценках опасных зон.\nРазведданные - основа любой кампании. Однако некоторые рыцари, помимо самой информации, проявляют интерес и к этому устройству.\nНапример, Лоэн.\n«Это же очень сложное устройство, а ты им так умело пользуешься?» - после того как Лоэн по обыкновению расспросил о расположении противника, он вдруг неожиданно добавил редкий комплимент: «Впечатляет».\nВнезапно получив похвалу от более опытного товарища примерно того же возраста, но с совершенно иной репутацией во всех смыслах, Мика был одновременно смущён и приятно удивлён.\nЛоэн, явно заинтригованный, начал задавать один вопрос за другим. А Мика, который редко обсуждал своё картографическое оборудование с кем-либо из нетехнического персонала, незаметно для себя увлёкся разговором.\n«Значит, с таким эффективным оборудованием ты наверняка знаешь немало мест, где обычно скапливаются враги, верно?» «Кстати, как ты его обычно обслуживаешь? У тебя есть запасные части?»\n...Может, этот «печально известный» опытный товарищ вовсе не так страшен, как гласят слухи?\nМика с энтузиазмом и подробно отвечал на все вопросы, а Лоэн, прищурившись, кивал, мысленно отмечая то, что его интересовало, и пропуская мимо ушей всё остальное.\nПосле нескольких таких бесед Мика постепенно заметил, что в тех местах, которыми Лоэн особенно интересовался, через несколько дней становилось заметно тише.\nЕсли связать новые раны, часто появлявшиеся на теле Лоэна, с его частыми кратковременными исчезновениями, всё это уже трудно было объяснить простым совпадением. Мика быстро пришёл к тревожному выводу: результаты его съёмки использовались Лоэном настолько эффективно и опасно, что это нельзя было описать иначе.\nИз соображений осторожности Мика начал пропускать в картах, которые передавал Лоэну, некоторые места скопления монстров, не связанные с боевыми маршрутами, а на вопросы Лоэна отвечал всё более уклончиво.\n«Э-э... я обо всём доложил!», «Всё-таки... лучше следовать единому командованию магистра ордена!».\nСтолкнувшись с уклончивостью Мики, Лоэн не стал настаивать на расспросах, а лишь многозначительно улыбнулся, и его взгляд то и дело - намеренно или случайно - задерживался на измерительном приборе, который Мика крепко прижимал к груди.\nС тех пор Мика стал гораздо внимательнее следить за сохранностью прибора: он проверял, убран ли журнал, прежде чем покинуть своё место, при передаче материалов несколько раз пересчитывал страницы и даже, отойдя на некоторое расстояние, оглядывался назад, словно опасаясь, что кто-то может следить за этим журналом.\nНо, несмотря на все эти меры, Лоэн продолжал действовать, словно он уже досконально знал информацию, которую Мика пытался скрыть... Это казалось настоящим волшебством.\nМика никак не мог этого понять, пока однажды вечером в экспедиционном лагере у костра не произошёл один случай.\nВ тот вечер Экберт громогласно заявил, что хочет показать новый фокус из Фонтейна, чтобы развлечь товарищей, но опьянение сыграло с ним злую шутку, и он случайно раскрыл секрет трюка.\nОн хотел показать грандиозный фокус с «обманной подменой», но по неосторожности слишком рано показал зрителям две почти одинаковые карты.\nСам фокус был довольно прост: незаметно подменить карту, выбранную зрителем, на замаскированную подделку, затем отвлечь внимание зрителя подделкой и за это короткое мгновение провернуть манипуляцию с настоящей картой. Жаль только, что всё закончилось, едва успев начаться.\nПод всеобщий хохот Мика неожиданно - сам не зная почему - вспомнил вопрос, который Лоэн задал ему очень давно.\n«Кстати, как ты обычно обслуживаешь своё оборудование? У тебя есть запасные части?»\nВ тот самый миг некоторые детали из прошлого вдруг сложились в ясную картину: таинственно исчезавшие запасные части и страницы журнала, которые иногда отказывались открываться из-за неисправностей...\nНе может же быть, чтобы кто-то, едва познакомившись, уже начал думать, как подшутить над коллегами?\nНе может же быть, чтобы кто-то на словах был таким дружелюбным и любопытным, а на самом деле вынашивал какие-то хитрые планы?\nИ уж точно не может быть, чтобы кто-то воспользовался мгновением, когда я моргнул, подменил мой измерительный прибор на какой-нибудь «псевдо-прибор», скопировал все разведданные, а потом с невероятной наглостью вернул всё обратно... правда?\nПри этой мысли Мика внезапно почувствовал на себе острый, как у хищной птицы, взгляд. Он резко поднял глаза - и увидел только Лоэна, который смеялся вместе со всеми, не глядя ни на кого конкретно.\nЭтот смех был открытым, искренним, даже по-настоящему тёплым... совсем как в тот раз, когда Лоэн впервые с таким энтузиазмом заговорил с Микой, без малейшей фальши."
      },
      {
        "Title": "Глаз Бога",
        "Context": "О том, как получить силу капитана, Лоэн давно глубоко размышлял.\nБез сомнения, капитан должен обладать силой, чтобы противостоять могучим монстрам и выдерживать натиск несметных полчищ врагов.\nСочетание разрушительной силы и выносливости - это про Варку, а также, похоже, про самого молодого капитана в истории Ордо Фавониус.\nНо для пятого отряда, который использует оружие дальнего боя, разрушительная сила и выносливость казались несовместимыми.\nЧтобы добиться большей разрушительной силы, нужен лук с более тугой тетивой и более тяжёлые, более пробивные стрелы.\nНо даже Лоэн мог носить с собой лишь ограниченное количество таких тяжёлых стрел. Когда они заканчивались, он вынужден был отходить в тыл за новыми - очевидный недостаток для затяжного боя.\nБолее того, Лоэн изначально не любил отходить с передовой. В конце концов, находиться на самом острие, лицом к лицу с врагом - вот что он по-настоящему жаждал в бою.\nТак есть ли способ совместить и то и другое? Молодой рыцарь задумался.\n«Возможно... это не совсем невозможно».\nСлучайно Лоэн заметил рыцарей, занятых подготовкой к смотру учений. Рядом с ними поблёскивали связки церемониальных копий, словно гигантские стрелы, ожидающие, когда их унесут.\n«Может быть, можно найти стрелу, которую после выстрела можно будет забирать?»\n«Или, может быть, совсем не обязательно стрелять?»\n«Ведь в ближнем бою разрушительная сила может оказаться даже больше? К тому же, возможно, и боль будет ощущаться сильнее».\n...\nНесколько десятков дней спустя состоялись плановые учения ордена. Но на этот раз появилось одно небольшое отличие - в строю отряда дальнего боя возникло копьё.\nЭто копьё атаковало слишком стремительно, и его владелец оказался в плотном кольце окружения.\n«Магистр ордена, вы уверены, что хотите назначить его заместителем капитана пятого отряда?» - издалека, наблюдая за учениями, спросил кардинал Шеймус.\n«М? Конечно. Посмотри, он же отлично взаимодействует с остальными, правда?»\n«Честно говоря, я не вижу никакого взаимодействия. Я вижу только крайне заметную живую мишень. И враги, и наши же стрелки сосредоточились на ней».\n«Ха-ха! Ничего страшного. Смотри, удары нашего отряда дальнего боя стали гораздо эффективнее! И Лоэн до сих пор не упал. Это доказывает, что тактика отличная!»\nЧто же здесь отличного? - чуть не выкрикнул в ответ Шеймус, но результаты говорили сами за себя.\n...\nВ тот день каждый получил то, что хотел, - или, по крайней мере, хоть что-то.\nПятый отряд получил заместителя капитана. Экспедиционный корпус получил «офицера по подавлению фронта». Замученный работой Шеймус получил день «отгула из-за головной боли». А Варка получил очередную «шутку про Шеймуса», под которую можно выпить.\nЧто касается Лоэна, с того дня он обрёл новый стиль боя и жизни, а также небольшой «стеклянный шарик», как он его называл, который иногда пригождался ему в заданиях."
      }
    ]
  },
  "Costumes": [
    {
      "Id": 212900,
      "Name": "Выкованный морозом",
      "Description": "Наряд Лоэна. Рыцарские доспехи выглядят куда более торжественно по сравнению с одеяниями времён его бытности искателем приключений. Но для Лоэна изменились лишь тяжесть снаряжения да взгляды окружающих. Неизменными же остались решимость сокрушать врагов и непреклонная одержимость, с которой он идёт вперёд.",
      "IsDefault": true
    }
  ],
  "CultivationItems": [
    104164,
    113085,
    101272,
    112013,
    104306,
    113073
  ],
  "NameCard": {
    "Name": "Милосердие",
    "Description": "Именная карта.\nМилосердие - последнее слово, которым можно было бы описать Лоэна. Но даже самые острые шипы вырастают из мягкой почвы.",
    "Icon": "UI_NameCardIcon_Lohen",
    "PicturePrefix": "UI_NameCardPic_Lohen"
  }
}